bacdive/__init__.py
bacdive/client.py
bacdive-1.0.0.dist-info/LICENSE
bacdive-1.0.0.dist-info/METADATA
bacdive-1.0.0.dist-info/WHEEL
bacdive-1.0.0.dist-info/top_level.txt
bacdive-1.0.0.dist-info/RECORD
