Metadata-Version: 2.1
Name: bacdive
Version: 1.0.0
Summary: BacDive-API - Programmatic Access to the BacDive Database
Home-page: https://bacdive.dsmz.de/
Author: Julia Koblitz
Author-email: julia.koblitz@dsmz.de
Keywords: microbiology bacteria strains phenotypes
Classifier: License :: OSI Approved :: MIT License
Classifier: Programming Language :: Python :: 3
Classifier: Intended Audience :: Science/Research
Classifier: Topic :: Scientific/Engineering :: Bio-Informatics
Requires-Python: >=3.6
License-File: LICENSE
Requires-Dist: python-keycloak
Requires-Dist: requests >=2.25.1
Requires-Dist: urllib3 >=1.26.5
